pygclip/__init__.py
pygclip/cli.py
pygclip/colors.py
pygclip/html.py
pygclip/io.py
pygclip/logging.py
pygclip-0.0.8.dist-info/DESCRIPTION.rst
pygclip-0.0.8.dist-info/METADATA
pygclip-0.0.8.dist-info/RECORD
pygclip-0.0.8.dist-info/WHEEL
pygclip-0.0.8.dist-info/entry_points.txt
pygclip-0.0.8.dist-info/metadata.json
pygclip-0.0.8.dist-info/top_level.txt
