Metadata-Version: 2.0
Name: pygclip
Version: 0.0.8
Summary: Pygmentize to clipboard for macOS.
Home-page: https://github.com/brymck/pygclip
Author: Bryan Lee McKelvey
Author-email: bryan.mckelvey@gmail.com
License: MIT
Platform: UNKNOWN
Classifier: License :: OSI Approved :: MIT License
Classifier: Programming Language :: Python
Classifier: Programming Language :: Python :: 3
Classifier: Programming Language :: Python :: 3.5
Classifier: Programming Language :: Python :: 3.6
Requires-Dist: pygments
Provides-Extra: dev
Requires-Dist: coverage; extra == 'dev'
Requires-Dist: flake8; extra == 'dev'
Requires-Dist: flake8-mypy; extra == 'dev'
Requires-Dist: pytest (>=3); extra == 'dev'
Requires-Dist: tox; extra == 'dev'
